{
  "updated_at": "2026-06-18T06:44:11.464349+00:00",
  "reports": [
    {
      "title": "6월 3주차 주간레포트",
      "week": "6월 3주차",
      "project": "자율주행 R&D",
      "blocked": false,
      "status": "submitted",
      "creator_id": "135d872b-594c-813a-a1f1-0002fbff0d85",
      "creator_name": "js_koti",
      "f1": "기반지도",
      "f2": "ㅇㅇ",
      "f3": "ㅇㅇ",
      "f4": "ㅇㅇ",
      "f5": "",
      "f6": "ㅇㅇ",
      "comment": "ㅇㅇ",
      "page_url": "https://app.notion.com/p/6-3-383ce6a25dc68055aafec4d0a994f3b7"
    },
    {
      "title": "",
      "week": "",
      "project": "",
      "blocked": false,
      "status": "pending",
      "creator_id": "382d872b-594c-8119-a8fb-00025edb3e90",
      "creator_name": "AI빅데이터팀",
      "f1": "",
      "f2": "",
      "f3": "",
      "f4": "",
      "f5": "",
      "f6": "",
      "comment": "",
      "page_url": "https://app.notion.com/p/383ce6a25dc680adbb5bd5d9ea545b13"
    },
    {
      "title": "6월 3주차 주간레포트",
      "week": "6월 3주차",
      "project": "자율주행 R&D",
      "blocked": true,
      "status": "submitted",
      "creator_id": "382d872b-594c-8119-a8fb-00025edb3e90",
      "creator_name": "AI빅데이터팀",
      "f1": "ㅇㅇ",
      "f2": "ㅇㅇ",
      "f3": "ㅇㅇ",
      "f4": "ㅇㅇ",
      "f5": "",
      "f6": "ㅇㅇ",
      "comment": "ㅇㅇ",
      "page_url": "https://app.notion.com/p/6-3-383ce6a25dc68038a55ad4664351b8ad"
    }
  ]
}